nus_logger/__init__.py
nus_logger/__main__.py
nus_logger/ble_nus.py
nus_logger/logger_controller.py
nus_logger/nus_logger.py
nus_logger/py.typed
nus_logger/utils.py
nus_logger-0.2.0.dist-info/METADATA
nus_logger-0.2.0.dist-info/WHEEL
nus_logger-0.2.0.dist-info/entry_points.txt
nus_logger-0.2.0.dist-info/licenses/LICENSE
nus_logger-0.2.0.dist-info/RECORD
