Metadata-Version: 2.4
Name: nus-logger
Version: 0.2.0
Summary: Nordic UART Service (NUS) BLE logger.
Project-URL: Homepage, https://github.com/smnmsr/nus-logger
Project-URL: Issues, https://github.com/smnmsr/nus-logger/issues
Project-URL: Source, https://github.com/smnmsr/nus-logger
Author: Simon M
License: MIT License
License-File: LICENSE
Keywords: BLE,NUS,Nordic,logging
Classifier: Environment :: Console
Classifier: Framework :: AsyncIO
Classifier: Intended Audience :: Developers
Classifier: License :: OSI Approved :: MIT License
Classifier: Operating System :: OS Independent
Classifier: Programming Language :: Python :: 3
Classifier: Programming Language :: Python :: 3 :: Only
Classifier: Programming Language :: Python :: 3.9
Classifier: Programming Language :: Python :: 3.10
Classifier: Programming Language :: Python :: 3.11
Classifier: Programming Language :: Python :: 3.12
Classifier: Topic :: Software Development :: Debuggers
Classifier: Topic :: System :: Logging
Classifier: Typing :: Typed
Requires-Python: >=3.9
Requires-Dist: bleak==0.22.2
Requires-Dist: colorama>=0.4.6; platform_system == 'Windows'
Provides-Extra: dev
Requires-Dist: colorama>=0.4.6; extra == 'dev'
Requires-Dist: pytest-asyncio>=0.23.0; extra == 'dev'
Requires-Dist: pytest>=8.0.0; extra == 'dev'
